Workbook

Sheet break_even_analysis
A1: Down Payment | B1: Term | C1: APR | D1: Monthly Payment | E1: Total Paid | F1: Total Interest | G1: 10% Down ($15,000) → Loan $135,000 | H1: 20% Down ($30,000) → Loan $120,000 | I1: Monthly Payment + Operating Costs | J1: Seasonal Operating costs | K1: Cost per event | L1: Cost Per Event Day | M1: Number of people needed per avg menu price
A2: 0 | B2: 5 years (60 mo) | C2: 0.06 | D2: 2900 | E2: 174000 | F2: 24000 | G2: $2,610 / mo → $156,600 total | H2: $2,320 / mo → $139,200 total | I2: =D2+6410 -> 9310 | J2: =(6410*6)+(D2*12) -> 73260 | K2: =J2/15 -> 4884 | L2: =(J2/41)*1.125 -> 2010.1829 | M2: =L2/16.85 -> 119.29869
A3: 0 | B3: 5 years (60 mo) | C3: 0.08 | D3: 3042 | E3: 182520 | F3: 32520 | G3: $2,738 / mo → $164,280 total | H3: $2,433 / mo → $145,980 total | I3: =D3+6410 -> 9452 | J3: =(6410*6)+(D3*12) -> 74964 | K3: =J3/15 -> 4997.6 | L3: =(J3/41)*1.125 -> 2056.939 | M3: =L3/16.85 -> 122.07353
A4: 0 | B4: 5 years (60 mo) | C4: 0.1 | D4: 3187 | E4: 191220 | F4: 41220 | G4: $2,868 / mo → $172,080 total | H4: $2,550 / mo → $153,000 total | I4: =D4+6410 -> 9597 | J4: =(6410*6)+(D4*12) -> 76704 | K4: =J4/15 -> 5113.6 | L4: =(J4/41)*1.125 -> 2104.6829 | M4: =L4/16.85 -> 124.907
A5: 0 | B5: 5 years (60 mo) | C5: 0.12 | D5: 3336 | E5: 200160 | F5: 50160 | G5: $3,002 / mo → $180,120 total | H5: $2,669 / mo → $160,140 total | I5: =D5+6410 -> 9746 | J5: =(6410*6)+(D5*12) -> 78492 | K5: =J5/15 -> 5232.8 | L5: =(J5/41)*1.125 -> 2153.7439 | M5: =L5/16.85 -> 127.81863
A6: 0 | B6: 7 years (84 mo) | C6: 0.06 | D6: 2192 | E6: 184128 | F6: 34128 | G6: $1,973 / mo → $165,732 total | H6: $1,754 / mo → $147,336 total | I6: =D6+6410 -> 8602 | J6: =(6410*6)+(D6*12) -> 64764 | K6: =J6/15 -> 4317.6 | L6: =(J6/41)*1.125 -> 1777.061 | M6: =L6/16.85 -> 105.46356
A7: 0 | B7: 7 years (84 mo) | C7: 0.08 | D7: 2274 | E7: 191016 | F7: 41016 | G7: $2,046 / mo → $171,888 total | H7: $1,819 / mo → $152,796 total | I7: =D7+6410 -> 8684 | J7: =(6410*6)+(D7*12) -> 65748 | K7: =J7/15 -> 4383.2 | L7: =(J7/41)*1.125 -> 1804.061 | M7: =L7/16.85 -> 107.06593
A8: 0 | B8: 7 years (84 mo) | C8: 0.1 | D8: 2360 | E8: 198240 | F8: 48240 | G8: $2,124 / mo → $178,416 total | H8: $1,888 / mo → $158,992 total | I8: =D8+6410 -> 8770 | J8: =(6410*6)+(D8*12) -> 66780 | K8: =J8/15 -> 4452 | L8: =(J8/41)*1.125 -> 1832.378 | M8: =L8/16.85 -> 108.74647
A9: 0 | B9: 7 years (84 mo) | C9: 0.12 | D9: 2451 | E9: 205884 | F9: 55884 | G9: $2,206 / mo → $185,304 total | H9: $1,961 / mo → $164,724 total | I9: =D9+6410 -> 8861 | J9: =(6410*6)+(D9*12) -> 67872 | K9: =J9/15 -> 4524.8 | L9: =(J9/41)*1.125 -> 1862.3415 | M9: =L9/16.85 -> 110.52472
A10: 0.1 | B10: 5 years (60 mo) | C10: 0.06 | D10: 2610 | E10: 156600 | I10: =D10+6410 -> 9020 | J10: =(6410*6)+(D10*12) -> 69780 | K10: =J10/15 -> 4652 | L10: =(J10/41)*1.125 -> 1914.6951 | M10: =L10/16.85 -> 113.63176
A11: 0.1 | B11: 5 years (60 mo) | C11: 0.08 | D11: 2738 | E11: 164280 | I11: =D11+6410 -> 9148 | J11: =(6410*6)+(D11*12) -> 71316 | K11: =J11/15 -> 4754.4 | L11: =(J11/41)*1.125 -> 1956.8415 | M11: =L11/16.85 -> 116.13302
A12: 0.1 | B12: 5 years (60 mo) | C12: 0.1 | D12: 2868 | E12: 172080 | I12: =D12+6410 -> 9278 | J12: =(6410*6)+(D12*12) -> 72876 | K12: =J12/15 -> 4858.4 | L12: =(J12/41)*1.125 -> 1999.6463 | M12: =L12/16.85 -> 118.67337
A13: 0.1 | B13: 5 years (60 mo) | C13: 0.12 | D13: 3002 | E13: 180120 | I13: =D13+6410 -> 9412 | J13: =(6410*6)+(D13*12) -> 74484 | K13: =J13/15 -> 4965.6 | L13: =(J13/41)*1.125 -> 2043.7683 | M13: =L13/16.85 -> 121.29189
A14: 0.1 | B14: 7 years (84 mo) | C14: 0.06 | D14: 1973 | E14: 165732 | I14: =D14+6410 -> 8383 | J14: =(6410*6)+(D14*12) -> 62136 | K14: =J14/15 -> 4142.4 | L14: =(J14/41)*1.125 -> 1704.9512 | M14: =L14/16.85 -> 101.18405
A15: 0.1 | B15: 7 years (84 mo) | C15: 0.08 | D15: 2046 | E15: 171888 | I15: =D15+6410 -> 8456 | J15: =(6410*6)+(D15*12) -> 63012 | K15: =J15/15 -> 4200.8 | L15: =(J15/41)*1.125 -> 1728.9878 | M15: =L15/16.85 -> 102.61055
A16: 0.1 | B16: 7 years (84 mo) | C16: 0.1 | D16: 2124 | E16: 178416 | I16: =D16+6410 -> 8534 | J16: =(6410*6)+(D16*12) -> 63948 | K16: =J16/15 -> 4263.2 | L16: =(J16/41)*1.125 -> 1754.6707 | M16: =L16/16.85 -> 104.13476
A17: 0.1 | B17: 7 years (84 mo) | C17: 0.12 | D17: 2206 | E17: 185304 | I17: =D17+6410 -> 8616 | J17: =(6410*6)+(D17*12) -> 64932 | K17: =J17/15 -> 4328.8 | L17: =(J17/41)*1.125 -> 1781.6707 | M17: =L17/16.85 -> 105.73714
A18: 0.2 | B18: 5 years (60 mo) | C18: 0.06 | D18: 2320 | E18: 139200 | I18: =D18+6410 -> 8730 | J18: =(6410*6)+(D18*12) -> 66300 | K18: =J18/15 -> 4420 | L18: =(J18/41)*1.125 -> 1819.2073 | M18: =L18/16.85 -> 107.96483
A19: 0.2 | B19: 5 years (60 mo) | C19: 0.08 | D19: 2433 | E19: 145980 | I19: =D19+6410 -> 8843 | J19: =(6410*6)+(D19*12) -> 67656 | K19: =J19/15 -> 4510.4 | L19: =(J19/41)*1.125 -> 1856.4146 | M19: =L19/16.85 -> 110.17298
A20: 0.2 | B20: 5 years (60 mo) | C20: 0.1 | D20: 2550 | E20: 153000 | I20: =D20+6410 -> 8960 | J20: =(6410*6)+(D20*12) -> 69060 | K20: =J20/15 -> 4604 | L20: =(J20/41)*1.125 -> 1894.939 | M20: =L20/16.85 -> 112.45929
A21: 0.2 | B21: 5 years (60 mo) | C21: 0.12 | D21: 2669 | E21: 160140 | I21: =D21+6410 -> 9079 | J21: =(6410*6)+(D21*12) -> 70488 | K21: =J21/15 -> 4699.2 | L21: =(J21/41)*1.125 -> 1934.122 | M21: =L21/16.85 -> 114.78469
... A25: 0.2 | B25: 7 years (84 mo) | C25: 0.12 | D25: 1961 | E25: 164724 | I25: =D25+6410 -> 8371 | J25: =(6410*6)+(D25*12) -> 61992 | K25: =J25/15 -> 4132.8 | L25: =(J25/41)*1.125 -> 1701 | M25: =L25/16.85 -> 100.94955

Sheet revenue_lowest_total
A1: number of customers | B1: revenue per event day | C1: revenue on season
A2: 20 | B2: =(A2*16.85) - break_even_analysis!$L$18 -> -1482.2073 | C2: =B2*41 -> -60770.5
A3: 21 | B3: =(A3*16.85) - break_even_analysis!$L$18 -> -1465.3573 | C3: =B3*41 -> -60079.65
A4: 22 | B4: =(A4*16.85) - break_even_analysis!$L$18 -> -1448.5073 | C4: =B4*41 -> -59388.8
A5: 23 | B5: =(A5*16.85) - break_even_analysis!$L$18 -> -1431.6573 | C5: =B5*41 -> -58697.95
A6: 24 | B6: =(A6*16.85) - break_even_analysis!$L$18 -> -1414.8073 | C6: =B6*41 -> -58007.1
A7: 25 | B7: =(A7*16.85) - break_even_analysis!$L$18 -> -1397.9573 | C7: =B7*41 -> -57316.25
A8: 26 | B8: =(A8*16.85) - break_even_analysis!$L$18 -> -1381.1073 | C8: =B8*41 -> -56625.4
A9: 27 | B9: =(A9*16.85) - break_even_analysis!$L$18 -> -1364.2573 | C9: =B9*41 -> -55934.55
A10: 28 | B10: =(A10*16.85) - break_even_analysis!$L$18 -> -1347.4073 | C10: =B10*41 -> -55243.7
A11: 29 | B11: =(A11*16.85) - break_even_analysis!$L$18 -> -1330.5573 | C11: =B11*41 -> -54552.85
A12: 30 | B12: =(A12*16.85) - break_even_analysis!$L$18 -> -1313.7073 | C12: =B12*41 -> -53862
A13: 31 | B13: =(A13*16.85) - break_even_analysis!$L$18 -> -1296.8573 | C13: =B13*41 -> -53171.15
... A232: 250 | B232: =(A232*16.85) - break_even_analysis!$L$18 -> 2393.2927 | C232: =B232*41 -> 98125

Sheet revenue_lowest_monthly
A1: number of customers | B1: revenue per event day | C1: revenue on season
A2: 20 | B2: =(A2*16.85) - break_even_analysis!$L$22 -> -1295.8415 | C2: =B2*41 -> -53129.5
A3: 21 | B3: =(A3*16.85) - break_even_analysis!$L$22 -> -1278.9915 | C3: =B3*41 -> -52438.65
A4: 22 | B4: =(A4*16.85) - break_even_analysis!$L$22 -> -1262.1415 | C4: =B4*41 -> -51747.8
A5: 23 | B5: =(A5*16.85) - break_even_analysis!$L$22 -> -1245.2915 | C5: =B5*41 -> -51056.95
A6: 24 | B6: =(A6*16.85) - break_even_analysis!$L$22 -> -1228.4415 | C6: =B6*41 -> -50366.1
A7: 25 | B7: =(A7*16.85) - break_even_analysis!$L$22 -> -1211.5915 | C7: =B7*41 -> -49675.25
A8: 26 | B8: =(A8*16.85) - break_even_analysis!$L$22 -> -1194.7415 | C8: =B8*41 -> -48984.4
A9: 27 | B9: =(A9*16.85) - break_even_analysis!$L$22 -> -1177.8915 | C9: =B9*41 -> -48293.55
A10: 28 | B10: =(A10*16.85) - break_even_analysis!$L$22 -> -1161.0415 | C10: =B10*41 -> -47602.7
A11: 29 | B11: =(A11*16.85) - break_even_analysis!$L$22 -> -1144.1915 | C11: =B11*41 -> -46911.85
A12: 30 | B12: =(A12*16.85) - break_even_analysis!$L$22 -> -1127.3415 | C12: =B12*41 -> -46221
A13: 31 | B13: =(A13*16.85) - break_even_analysis!$L$22 -> -1110.4915 | C13: =B13*41 -> -45530.15
... A232: 250 | B232: =(A232*16.85) - break_even_analysis!$L$22 -> 2579.6585 | C232: =B232*41 -> 105766

Sheet 10pct down
A1: Term | B1: APR | C1: Monthly Payment | D1: Monthly Payment + Operating Costs | E1: Seasonal Operating costs | F1: Cost per event | G1: Cost Per Event Day | H1: Number of people needed per avg menu price
A2: 5 years (60 mo) | B2: 0.06 | C2: 2610 | D2: =C2+6410 -> 9020 | E2: =(6410*6)+(C2*12) -> 69780 | F2: =E2/15 -> 4652 | G2: =E2/41 -> 1701.9512 | H2: =G2/14.82 -> 114.84151
A3: 5 years (60 mo) | B3: 0.08 | C3: 2738 | D3: =C3+6410 -> 9148 | E3: =(6410*6)+(C3*12) -> 71316 | F3: =E3/15 -> 4754.4 | G3: =E3/41 -> 1739.4146 | H3: =G3/14.82 -> 117.36941
A4: 5 years (60 mo) | B4: 0.1 | C4: 2868 | D4: =C4+6410 -> 9278 | E4: =(6410*6)+(C4*12) -> 72876 | F4: =E4/15 -> 4858.4 | G4: =E4/41 -> 1777.4634 | H4: =G4/14.82 -> 119.9368
A5: 5 years (60 mo) | B5: 0.12 | C5: 3002 | D5: =C5+6410 -> 9412 | E5: =(6410*6)+(C5*12) -> 74484 | F5: =E5/15 -> 4965.6 | G5: =E5/41 -> 1816.6829 | H5: =G5/14.82 -> 122.58319
A6: 7 years (84 mo) | B6: 0.06 | C6: 1973 | D6: =C6+6410 -> 8383 | E6: =(6410*6)+(C6*12) -> 62136 | F6: =E6/15 -> 4142.4 | G6: =E6/41 -> 1515.5122 | H6: =G6/14.82 -> 102.26128
A7: 7 years (84 mo) | B7: 0.08 | C7: 2046 | D7: =C7+6410 -> 8456 | E7: =(6410*6)+(C7*12) -> 63012 | F7: =E7/15 -> 4200.8 | G7: =E7/41 -> 1536.878 | H7: =G7/14.82 -> 103.70297
A8: 7 years (84 mo) | B8: 0.1 | C8: 2124 | D8: =C8+6410 -> 8534 | E8: =(6410*6)+(C8*12) -> 63948 | F8: =E8/15 -> 4263.2 | G8: =E8/41 -> 1559.7073 | H8: =G8/14.82 -> 105.24341
A9: 7 years (84 mo) | B9: 0.12 | C9: 2206 | D9: =C9+6410 -> 8616 | E9: =(6410*6)+(C9*12) -> 64932 | F9: =E9/15 -> 4328.8 | G9: =E9/41 -> 1583.7073 | H9: =G9/14.82 -> 106.86284

Sheet 20pct down
A1: Term | B1: APR | C1: Monthly Payment | D1: Monthly Payment + Operating Costs | E1: Seasonal Operating costs | F1: Cost per event | G1: Cost Per Event Day | H1: Number of people needed per avg menu price
A2: 5 years (60 mo) | B2: 0.06 | C2: 2320 | D2: =C2+6410 -> 8730 | E2: =(6410*6)+(C2*12) -> 66300 | F2: =E2/15 -> 4420 | G2: =E2/41 -> 1617.0732 | H2: =G2/14.82 -> 109.11425
A3: 5 years (60 mo) | B3: 0.08 | C3: 2433 | D3: =C3+6410 -> 8843 | E3: =(6410*6)+(C3*12) -> 67656 | F3: =E3/15 -> 4510.4 | G3: =E3/41 -> 1650.1463 | H3: =G3/14.82 -> 111.34591
A4: 5 years (60 mo) | B4: 0.1 | C4: 2550 | D4: =C4+6410 -> 8960 | E4: =(6410*6)+(C4*12) -> 69060 | F4: =E4/15 -> 4604 | G4: =E4/41 -> 1684.3902 | H4: =G4/14.82 -> 113.65656
A5: 5 years (60 mo) | B5: 0.12 | C5: 2669 | D5: =C5+6410 -> 9079 | E5: =(6410*6)+(C5*12) -> 70488 | F5: =E5/15 -> 4699.2 | G5: =E5/41 -> 1719.2195 | H5: =G5/14.82 -> 116.00671
A6: 7 years (84 mo) | B6: 0.06 | C6: 1754 | D6: =C6+6410 -> 8164 | E6: =(6410*6)+(C6*12) -> 59508 | F6: =E6/15 -> 3967.2 | G6: =E6/41 -> 1451.4146 | H6: =G6/14.82 -> 97.93621
A7: 7 years (84 mo) | B7: 0.08 | C7: 1819 | D7: =C7+6410 -> 8229 | E7: =(6410*6)+(C7*12) -> 60288 | F7: =E7/15 -> 4019.2 | G7: =E7/41 -> 1470.439 | H7: =G7/14.82 -> 99.219907
A8: 7 years (84 mo) | B8: 0.1 | C8: 1888 | D8: =C8+6410 -> 8298 | E8: =(6410*6)+(C8*12) -> 61116 | F8: =E8/15 -> 4074.4 | G8: =E8/41 -> 1490.6341 | H8: =G8/14.82 -> 100.5826
A9: 7 years (84 mo) | B9: 0.12 | C9: 1961 | D9: =C9+6410 -> 8371 | E9: =(6410*6)+(C9*12) -> 61992 | F9: =E9/15 -> 4132.8 | G9: =E9/41 -> 1512 | H9: =G9/14.82 -> 102.02429
